{
"autoplayBgm":false,"autoplayBgs":false,"battleback1Name":"","battleback2Name":"","bgm":{"name":"","pan":0,"pitch":100,"volume":90},"bgs":{"name":"","pan":0,"pitch":100,"volume":90},"disableDashing":false,"displayName":"","encounterList":[],"encounterStep":30,"height":13,"note":"","parallaxLoopX":false,"parallaxLoopY":false,"parallaxName":"","parallaxShow":true,"parallaxSx":0,"parallaxSy":0,"scrollType":0,"specifyBattleback":false,"tilesetId":3,"width":17,
"data":[0,0,0,0,0,0,0,0,0,0,0,0,0,0,0,0,0,0,0,0,0,0,0,0,0,0,0,0,0,0,0,0,0,0,0,0,0,2371,2369,2369,2369,2369,2369,2369,2369,2373,0,0,0,0,0,0,0,0,2368,7043,7042,7042,7042,7042,7042,7046,2368,0,0,0,0,0,0,0,0,2368,7049,7048,7048,7048,7048,7048,7052,2368,0,0,0,0,0,0,0,0,2368,4098,4084,4084,4084,4084,4084,4100,2368,0,0,0,0,0,0,0,0,2368,4080,4064,4064,4064,4064,4064,4088,2368,0,0,0,0,0,0,0,0,2368,4080,4064,4064,4064,4064,4064,4088,2368,0,0,0,0,0,0,0,0,2368,4104,4092,4092,4092,4092,4092,4102,2368,0,0,0,0,0,0,0,0,2377,2369,2369,2369,2369,2369,2369,2369,2375,0,0,0,0,0,0,0,0,0,0,0,0,0,0,0,0,0,0,0,0,0,0,0,0,0,0,0,0,0,0,0,0,0,0,0,0,0,0,0,0,0,0,0,0,0,0,0,0,0,0,0,0,0,0,0,0,0,0,0,0,0,0,0,0,0,0,0,0,0,0,0,0,0,0,0,0,0,0,0,0,0,0,0,0,0,0,0,0,0,0,0,0,0,0,0,0,0,0,0,0,0,0,0,0,0,0,0,0,0,0,0,0,0,0,0,0,0,0,0,0,0,0,0,0,0,0,0,0,0,0,0,0,0,0,0,0,0,0,0,0,0,0,0,0,0,0,0,0,0,0,0,0,0,0,0,0,0,0,0,0,0,0,0,0,0,0,0,0,0,0,0,0,0,0,0,0,0,0,0,0,0,0,0,0,0,0,0,0,0,0,0,0,0,0,0,0,0,0,0,0,0,0,0,0,0,0,0,0,0,0,0,0,0,0,0,0,0,0,0,0,0,0,0,0,0,0,0,0,0,0,0,0,0,0,0,0,0,0,0,0,0,0,0,0,0,0,0,0,0,0,0,0,0,0,0,0,0,0,0,0,0,0,0,0,0,0,0,0,0,0,0,0,0,0,0,0,0,0,0,0,0,0,0,0,0,0,0,0,0,0,0,0,0,0,0,0,0,0,0,0,0,0,0,0,0,0,0,0,0,0,0,0,0,0,0,0,0,0,0,0,0,0,0,0,0,0,0,0,0,0,0,0,0,0,0,0,0,0,0,0,0,0,0,0,0,0,0,0,0,0,0,0,0,0,0,0,0,0,0,0,0,0,0,0,0,0,0,0,0,0,0,0,0,0,0,0,0,0,0,0,0,0,0,0,0,0,0,0,0,0,0,0,0,0,0,0,0,0,0,0,0,0,0,0,0,233,233,0,0,0,0,0,0,0,0,0,0,0,0,0,0,0,251,251,0,0,0,0,0,0,0,0,0,0,0,0,0,0,0,0,0,0,0,0,0,0,0,0,0,0,0,0,0,0,0,0,0,0,0,0,0,0,0,0,0,0,0,0,0,0,0,0,0,0,0,0,0,0,0,0,0,0,0,0,0,0,0,0,0,0,0,0,0,0,0,0,0,0,0,0,0,0,0,0,0,0,0,0,0,0,0,0,0,0,0,0,0,0,0,0,0,0,0,0,0,0,0,0,0,0,0,0,0,0,0,0,0,0,0,0,0,0,0,0,0,0,0,0,0,0,0,0,0,0,0,0,194,0,0,0,0,0,0,0,0,0,0,0,0,0,242,0,0,176,0,226,227,0,0,0,0,0,0,0,0,0,0,250,0,0,184,0,234,235,0,0,0,0,0,0,0,0,0,0,218,0,0,0,0,225,225,0,0,0,0,0,0,0,0,0,0,208,0,0,0,0,243,243,0,0,0,0,0,0,0,0,0,0,216,0,0,0,0,241,241,0,0,0,0,0,0,0,0,0,0,0,0,0,0,0,0,0,0,0,0,0,0,0,0,0,0,0,0,0,0,0,0,0,0,0,0,0,0,0,0,0,0,0,0,0,0,0,0,0,0,0,0,0,0,0,0,0,0,0,0,0,0,0,0,0,0,0,0,0,0,0,0,0,0,0,0,0,0,0,0,0,0,0,0,0,0,0,0,0,0,0,0,0,0,0,0,0,0,0,0,0,0,0,0,0,0,0,0,0,0,0,0,0,0,0,0,0,0,0,0,0,0,0,0,0,0,0,0,0,0,0,0,0,0,0,0,0,0,0,0,0,0,0,0,0,0,0,0,0,0,0,0,0,5,0,0,0,0,0,0,0,0,0,0,0,0,0,0,0,0,0,0,0,0,0,0,0,0,0,0,0,0,0,0,0,0,0,0,0,0,0,0,0,0,0,0,0,0,0,0,0,0,0,0,0,0,0,0,0,0,0,0,0,0,0,0,0,0,0,0,0,0,0,0,0,0,0,0,0,0,0,0,0,0,0,0,0,0,0,0,0,0,0,0,0,0,0,0,0,0,0,0,0,0,0,0,0,0,0,0,0,0,0,0,0,0,0,0,0,0,0,0,0,0,0,0,0,0,0,0,0,0,0,0,0,0,0,0,0,0,0,0,0,0,0,0,0,0,0,0,0,0,0,0,0,0,0,0,0,0,0,0,0,0,0,0,0,0,0,0,0,0,0,0,0,0,0,0,0,0,0,0,0,0,0,0,0,0,0,0,0,0,0,0,0,0,0,0,0,0,0,0,0,0,0,0,0,0,0,0,0,0,0,0,0,0,0,0,0,0,0,0,0,0,0,0,0,0,0,0,0,0,0,0,0,0,0,0,0,0,0,0,0,0,0,0,0,0,0,0,0,0,0,0,0,0,0,0,0,0,0,0,0,0,0,0,0,0,0,0,0,0,0,0,0,0,0,0,0,0,0,0,0,0,0,0,0,0,0,0,0,0,0,0,0,0,0,0,0,0,0,0,0,0,0,0,0,0,0,0,0,0,0,0,0,0,0,0,0,0,0,0,0,0,0,0,0,0,0,0,0,0,0,0,0,0,0,0,0,0,0,0,0,0,0,0,0,0,0,0,0,0,0,0,0,0,0,0,0,0,0,0,0,0,0,0],
"events":[
null,
{"id":1,"name":"NPC_001","note":"","pages":[{"conditions":{"actorId":1,"actorValid":false,"itemId":1,"itemValid":false,"selfSwitchCh":"A","selfSwitchValid":false,"switch1Id":1,"switch1Valid":false,"switch2Id":1,"switch2Valid":false,"variableId":1,"variableValid":false,"variableValue":0},"directionFix":false,"image":{"tileId":0,"characterName":"Actor3","direction":2,"pattern":1,"characterIndex":6},"list":[{"code":101,"indent":0,"parameters":["Actor3",6,0,2]},{"code":401,"indent":0,"parameters":["D M:"]},{"code":401,"indent":0,"parameters":["- No te voy a decir que hay un lado bueno"]},{"code":401,"indent":0,"parameters":["o malo, decide tu mism@, estas con nosotros"]},{"code":401,"indent":0,"parameters":["en esta lucha?"]},{"code":102,"indent":0,"parameters":[["Sí","No"],1,0,2,0]},{"code":402,"indent":0,"parameters":[0,"Sí"]},{"code":101,"indent":1,"parameters":["Actor3",6,0,2]},{"code":401,"indent":1,"parameters":["D M:"]},{"code":401,"indent":1,"parameters":["- ¡¡BIENVENIDO!!"]},{"code":401,"indent":1,"parameters":["¿COMO TE LLAMAS?"]},{"code":303,"indent":1,"parameters":[1,8]},{"code":101,"indent":1,"parameters":["Actor3",6,0,2]},{"code":401,"indent":1,"parameters":["D M:"]},{"code":401,"indent":1,"parameters":["- ERES, EL HÉROE"]},{"code":401,"indent":1,"parameters":["SIENTO NO PODER DECIRTE MI NOMBRE, SI LO "]},{"code":401,"indent":1,"parameters":["DIJESE MORIRIAS POR UNA MALDICION"]},{"code":230,"indent":1,"parameters":[120]},{"code":201,"indent":1,"parameters":[0,5,21,49,8,0]},{"code":0,"indent":1,"parameters":[]},{"code":402,"indent":0,"parameters":[1,"No"]},{"code":101,"indent":1,"parameters":["Actor3",6,0,2]},{"code":401,"indent":1,"parameters":["D M:"]},{"code":401,"indent":1,"parameters":["- Lo siento amigo, no pienso decirte nada "]},{"code":401,"indent":1,"parameters":["más, que tengas un buen día, adiós."]},{"code":230,"indent":1,"parameters":[120]},{"code":201,"indent":1,"parameters":[0,2,11,15,2,0]},{"code":0,"indent":1,"parameters":[]},{"code":404,"indent":0,"parameters":[]},{"code":0,"indent":0,"parameters":[]}],"moveFrequency":3,"moveRoute":{"list":[{"code":0,"parameters":[]}],"repeat":true,"skippable":false,"wait":false},"moveSpeed":3,"moveType":0,"priorityType":1,"stepAnime":false,"through":false,"trigger":0,"walkAnime":true}],"x":7,"y":5},
{"id":2,"name":"EV002","note":"","pages":[{"conditions":{"actorId":1,"actorValid":false,"itemId":1,"itemValid":false,"selfSwitchCh":"A","selfSwitchValid":false,"switch1Id":1,"switch1Valid":false,"switch2Id":1,"switch2Valid":false,"variableId":1,"variableValid":false,"variableValue":0},"directionFix":false,"image":{"characterIndex":0,"characterName":"!Door1","direction":2,"pattern":1,"tileId":0},"list":[{"code":250,"indent":0,"parameters":[{"name":"Open1","pan":0,"pitch":100,"volume":90}]},{"code":205,"indent":0,"parameters":[0,{"list":[{"code":17},{"code":15,"parameters":[3]},{"code":18},{"code":15,"parameters":[3]},{"code":19},{"code":37},{"code":0}],"repeat":false,"skippable":false,"wait":true}]},{"code":505,"indent":0,"parameters":[{"code":17}]},{"code":505,"indent":0,"parameters":[{"code":15,"parameters":[3]}]},{"code":505,"indent":0,"parameters":[{"code":18}]},{"code":505,"indent":0,"parameters":[{"code":15,"parameters":[3]}]},{"code":505,"indent":0,"parameters":[{"code":19}]},{"code":505,"indent":0,"parameters":[{"code":37}]},{"code":205,"indent":0,"parameters":[-1,{"list":[{"code":12},{"code":0}],"repeat":false,"skippable":true,"wait":true}]},{"code":505,"indent":0,"parameters":[{"code":12}]},{"code":250,"indent":0,"parameters":[{"name":"Move1","pan":0,"pitch":100,"volume":90}]},{"code":201,"indent":0,"parameters":[0,2,11,15,0,0]},{"code":0,"indent":0,"parameters":[]}],"moveFrequency":3,"moveRoute":{"list":[{"code":0,"parameters":[]}],"repeat":true,"skippable":false,"wait":false},"moveSpeed":3,"moveType":0,"priorityType":1,"stepAnime":false,"through":false,"trigger":1,"walkAnime":false}],"x":7,"y":9},
{"id":3,"name":"EV003","note":"","pages":[{"conditions":{"actorId":1,"actorValid":false,"itemId":1,"itemValid":false,"selfSwitchCh":"A","selfSwitchValid":false,"switch1Id":1,"switch1Valid":false,"switch2Id":1,"switch2Valid":false,"variableId":1,"variableValid":false,"variableValue":0},"directionFix":false,"image":{"tileId":0,"characterName":"People3","direction":2,"pattern":1,"characterIndex":6},"list":[{"code":352,"indent":0,"parameters":[]},{"code":0,"indent":0,"parameters":[]}],"moveFrequency":3,"moveRoute":{"list":[{"code":0,"parameters":[]}],"repeat":true,"skippable":false,"wait":false},"moveSpeed":3,"moveType":0,"priorityType":1,"stepAnime":false,"through":false,"trigger":0,"walkAnime":true}],"x":5,"y":5}
]
}